{
  "updated_utc": "2026-06-21T14:56:00Z",
  "entries": [
    {
      "date": "June 20, 2026",
      "reward": "15 Energy",
      "url": "https://travel-town-app.com/sDq5jMho",
      "source": "frvr"
    },
    {
      "date": "June 20, 2026",
      "reward": "10 Energy",
      "url": "https://travel-town-app.com/ci2xiIRQ",
      "source": "frvr"
    },
    {
      "date": "June 20, 2026",
      "reward": "25 Energy",
      "url": "https://travel-town-app.com/yFSQDSw",
      "source": "frvr"
    },
    {
      "date": "June 20, 2026",
      "reward": "10 Energy",
      "url": "https://api.traveltowngame.net/public/rewardLinks/getLink/yqdOIBfN_TRADING",
      "source": "frvr"
    },
    {
      "date": "June 20, 2026",
      "reward": "20 Energy",
      "url": "https://api.traveltowngame.net/public/rewardLinks/getLink/J0lnZh1h_WA",
      "source": "frvr"
    },
    {
      "date": "June 19, 2026",
      "reward": "15 Energy",
      "url": "https://travel-town-app.com/kQhmOVLB",
      "source": "frvr"
    },
    {
      "date": "June 19, 2026",
      "reward": "10 Energy",
      "url": "https://travel-town-app.com/Ut7isak2",
      "source": "frvr"
    },
    {
      "date": "June 19, 2026",
      "reward": "25 Energy",
      "url": "https://travel-town-app.com/DcZVPbJd",
      "source": "frvr"
    },
    {
      "date": "June 18, 2026",
      "reward": "10 Energy",
      "url": "https://api.traveltowngame.net/public/rewardLinks/getLink/6bEbuf4t_TRADING",
      "source": "frvr"
    },
    {
      "date": "June 18, 2026",
      "reward": "20 Energy",
      "url": "https://travel-town-app.com/kKcUbH0k",
      "source": "frvr"
    },
    {
      "date": "June 18, 2026",
      "reward": "15 Energy",
      "url": "https://travel-town-app.com/X2ZN5HOy",
      "source": "frvr"
    },
    {
      "date": "June 18, 2026",
      "reward": "10 Energy",
      "url": "https://travel-town-app.com/C3OfLNpz",
      "source": "frvr"
    },
    {
      "date": "June 18, 2026",
      "reward": "25 Energy",
      "url": "https://travel-town-app.com/bCZJH09B",
      "source": "frvr"
    },
    {
      "date": "June 18, 2026",
      "reward": "20 Energy",
      "url": "https://api.traveltowngame.net/public/rewardLinks/getLink/TaST4GUX_WA",
      "source": "frvr"
    },
    {
      "date": "June 17, 2026",
      "reward": "10 Energy",
      "url": "https://api.traveltowngame.net/public/rewardLinks/getLink/PLht8y1w_TRADING",
      "source": "frvr"
    },
    {
      "date": "June 17, 2026",
      "reward": "15 Energy",
      "url": "https://travel-town-app.com/KW0FY3l4",
      "source": "frvr"
    },
    {
      "date": "June 17, 2026",
      "reward": "10 Energy",
      "url": "https://travel-town-app.com/3l1BnY5G",
      "source": "frvr"
    },
    {
      "date": "June 17, 2026",
      "reward": "25 Energy",
      "url": "https://travel-town-app.com/qJ4gtDl7",
      "source": "frvr"
    },
    {
      "date": "June 17, 2026",
      "reward": "20 Energy",
      "url": "https://api.traveltowngame.net/public/rewardLinks/getLink/7fX4Iupx_WA",
      "source": "frvr"
    },
    {
      "date": "June 17, 2026",
      "reward": "10 Energy",
      "url": "https://api.traveltowngame.net/public/rewardLinks/getLink/fiFnuKou_TRADING",
      "source": "frvr"
    }
  ]
}